{
  "assembly_contract_id": "aps_evidence_report_assembly_v1",
  "evidence_report_checksum": "92fe4b7416e930cad96d17744dea9eb649084f7a3e88b081b83e1ac8179be9ae",
  "evidence_report_id": "0c91838bae985d967fdb68c914c7f5856a84a32f98b7f97ce6a4186fb44e1b4e",
  "generated_at_utc": "2026-03-11T18:19:22.775388Z",
  "schema_id": "aps.evidence_report.v1",
  "schema_version": 1,
  "sectioning_contract_id": "aps_evidence_report_sectioning_v1",
  "sections": [
    {
      "accession_number": "ML-REPORT-EXPORT-PACKAGE-API-1",
      "chunking_contract_id": "aps_chunking_v1",
      "citation_count": 2,
      "citations": [
        {
          "chunk_id": "chunk-report-export-package-api-1",
          "chunk_ordinal": 0,
          "citation_id": "b71b43d1bb3d4d10f9914fb117d3db4e866f0c670c530ed6dbbe1bbecdcdee99",
          "citation_label": "APS-CIT-00001",
          "citation_ordinal": 1,
          "end_char": 16,
          "highlight_spans": [
            {
              "chunk_end": 5,
              "chunk_start": 0,
              "snippet_end": 5,
              "snippet_start": 0
            },
            {
              "chunk_end": 11,
              "chunk_start": 6,
              "snippet_end": 11,
              "snippet_start": 6
            }
          ],
          "snippet_end_char": 16,
          "snippet_start_char": 0,
          "snippet_text": "alpha alpha beta",
          "start_char": 0
        },
        {
          "chunk_id": "chunk-report-export-package-api-2",
          "chunk_ordinal": 1,
          "citation_id": "cb4cf1d0f35ffcb8257c66d29c9fd1a75756dd73287b138bc3ada59a9a8e5250",
          "citation_label": "APS-CIT-00002",
          "citation_ordinal": 2,
          "end_char": 28,
          "highlight_spans": [
            {
              "chunk_end": 5,
              "chunk_start": 0,
              "snippet_end": 5,
              "snippet_start": 0
            }
          ],
          "snippet_end_char": 11,
          "snippet_start_char": 0,
          "snippet_text": "alpha gamma",
          "start_char": 17
        }
      ],
      "content_contract_id": "aps_content_units_v1",
      "content_id": "content-report-export-package-api-1",
      "group_id": "4b1c09d29b5068db190dec9ae7880bc4b3b912a91f5e291826645b46ffe05091",
      "run_id": "run-report-export-package-api-1",
      "section_id": "88e691f7a19a7afe86c99e4f6cba18eee41d8a431b7a170c2f030774f3a0557d",
      "section_ordinal": 1,
      "section_type": "evidence_group",
      "target_id": "target-report-export-package-api-1",
      "title": "Accession ML-REPORT-EXPORT-PACKAGE-API-1 / Content content-report-export-package-api-1"
    },
    {
      "accession_number": null,
      "chunking_contract_id": "aps_chunking_v1",
      "citation_count": 1,
      "citations": [
        {
          "chunk_id": "chunk-report-export-package-api-3",
          "chunk_ordinal": 0,
          "citation_id": "310b7ec6881d3efab68e555a47b92fbc31b6c9eda02a372ecdf721b9350a4e63",
          "citation_label": "APS-CIT-00003",
          "citation_ordinal": 3,
          "end_char": 11,
          "highlight_spans": [
            {
              "chunk_end": 5,
              "chunk_start": 0,
              "snippet_end": 5,
              "snippet_start": 0
            }
          ],
          "snippet_end_char": 11,
          "snippet_start_char": 0,
          "snippet_text": "alpha delta",
          "start_char": 0
        }
      ],
      "content_contract_id": "aps_content_units_v1",
      "content_id": "content-report-export-package-api-2",
      "group_id": "5878626888e35d2b2f2a9131636846d77c722e614a0d0eb178e33f61aa63a0f2",
      "run_id": "run-report-export-package-api-1",
      "section_id": "8212908819a76b2b79f65f6e60f564e2cca2312bf0c2e6a394a0fbd31fc0774d",
      "section_ordinal": 2,
      "section_type": "evidence_group",
      "target_id": "target-report-export-package-api-2",
      "title": "Content content-report-export-package-api-2"
    }
  ],
  "source_citation_pack": {
    "citation_pack_checksum": "72047200d9091f4134514a57d8a7f77038e25c3e73bdb0c6d324b6290b0c7807",
    "citation_pack_id": "6bb4b8a7cb8203356972276f7de826f417637773b90d4a49d21844cdc4321709",
    "citation_pack_ref": "app\\storage\\connectors\\reports\\run_run-report-export-package-api-1_6bb4b8a7cb8203356972276f_aps_evidence_citation_pack_v1.json",
    "derivation_contract_id": "aps_evidence_citation_derivation_v1",
    "schema_id": "aps.evidence_citation_pack.v1",
    "schema_version": 1,
    "source_bundle": {
      "bundle_checksum": "0ad8b9a276cc53d8829a14d5763124956dac92b3fae2040976a2ca8427a59ea8",
      "bundle_id": "3cb329bc11e0cfa8eb69c419d5eba02da0162f8d6a644685a23be0d8c06784ed",
      "bundle_ref": "app\\storage\\connectors\\reports\\run_run-report-export-package-api-1_3cb329bc11e0cfa8eb69c419d5eba02da0162f8d6a644685a23be0d8c06784ed_aps_evidence_bundle_v1.json",
      "mode": "query",
      "query": "alpha",
      "query_tokens": [
        "alpha"
      ],
      "request_identity_hash": "9a16e5dbf5eb3fba54834a4a73ad40ed7b57a85dcde81286d05fed07646d31d8",
      "run_id": "run-report-export-package-api-1",
      "schema_id": "aps.evidence_bundle.v1",
      "schema_version": 1,
      "snapshot": {
        "db_fingerprint": "6f8c353f799a5f9530618aaee5b6b56febbfba9b4809b7ee6328061c1070c84b",
        "index_max_updated_at_utc": "2026-03-11T18:19:22.737376Z",
        "index_row_count": 3,
        "index_state_hash": "db2bf68a4f465da1a8b9a64ac75a592069012ea43d05bff24eb38da60dc8b6d3",
        "read_scope": {
          "filters": {
            "accession_numbers": null,
            "chunking_contract_id": null,
            "content_contract_id": null,
            "content_ids": null,
            "normalization_contract_id": null,
            "target_ids": null
          },
          "run_id": "run-report-export-package-api-1"
        },
        "snapshot_completed_at_utc": "2026-03-11T18:19:22.743375Z",
        "snapshot_contract_id": "aps_evidence_snapshot_v1",
        "snapshot_started_at_utc": "2026-03-11T18:19:22.742368Z"
      },
      "total_groups": 2,
      "total_hits": 3
    },
    "total_citations": 3,
    "total_groups": 2
  },
  "total_citations": 3,
  "total_groups": 2,
  "total_sections": 2
}
